entrytest/__init__.py
entrytest/app.py
entrytest-0.31.data/scripts/entrytest.cmd
entrytest-0.31.dist-info/METADATA
entrytest-0.31.dist-info/WHEEL
entrytest-0.31.dist-info/entry_points.txt
entrytest-0.31.dist-info/top_level.txt
entrytest-0.31.dist-info/RECORD
