Metadata-Version: 2.1
Name: entrytest
Version: 0.31
Summary: test pip entry point
Author: FacerAin
Author-email: syw5141@gmail.com
License: MIT
Classifier: Programming Language :: Python :: 3
Classifier: License :: OSI Approved :: MIT License
Classifier: Operating System :: OS Independent
